setup.py
sample_first_distributions/Binomialdistribution.py
sample_first_distributions/Gaussiandistribution.py
sample_first_distributions/Generaldistribution.py
sample_first_distributions/__init__.py
sample_first_distributions.egg-info/PKG-INFO
sample_first_distributions.egg-info/SOURCES.txt
sample_first_distributions.egg-info/dependency_links.txt
sample_first_distributions.egg-info/not-zip-safe
sample_first_distributions.egg-info/top_level.txt