Metadata-Version: 1.0
Name: sample-first-distributions
Version: 0.1
Summary: Gaussian distributions
Home-page: UNKNOWN
Author: Efioesien Efiom
Author-email: efioesien@gmail.com
License: UNKNOWN
Platform: UNKNOWN
